MANIFEST.in
README.md
pytest_httpretty.py
setup.py
test_pytest_httpretty.py
tox.ini
pytest_httpretty.egg-info/PKG-INFO
pytest_httpretty.egg-info/SOURCES.txt
pytest_httpretty.egg-info/dependency_links.txt
pytest_httpretty.egg-info/entry_points.txt
pytest_httpretty.egg-info/not-zip-safe
pytest_httpretty.egg-info/requires.txt
pytest_httpretty.egg-info/top_level.txt