Metadata-Version: 1.1
Name: pytest-httpretty
Version: 0.2.0
Summary: A thin wrapper of HTTPretty for pytest
Home-page: http://github.com/papaeye/pytest-httpretty
Author: papaeye
Author-email: papaeye@gmail.com
License: BSD License
Keywords: pytest httpretty http stub mock
Platform: any
Classifier: Development Status :: 3 - Alpha
Classifier: License :: OSI Approved :: BSD License
Classifier: Operating System :: OS Independent
Classifier: Programming Language :: Python
Classifier: Programming Language :: Python :: 2
Classifier: Programming Language :: Python :: 2.7
Classifier: Programming Language :: Python :: 3
Classifier: Programming Language :: Python :: 3.3
